pcbasic/__init__.py
pcbasic/__main__.py
pcbasic/config.py
pcbasic/debug.py
pcbasic/guard.py
pcbasic/info.py
pcbasic/main.py
pcbasic/basic/__init__.py
pcbasic/basic/api.py
pcbasic/basic/basicevents.py
pcbasic/basic/clock.py
pcbasic/basic/codepage.py
pcbasic/basic/console.py
pcbasic/basic/dos.py
pcbasic/basic/eventcycle.py
pcbasic/basic/extensions.py
pcbasic/basic/implementation.py
pcbasic/basic/interpreter.py
pcbasic/basic/iostreams.py
pcbasic/basic/machine.py
pcbasic/basic/mlparser.py
pcbasic/basic/program.py
pcbasic/basic/sound.py
pcbasic/basic/state.py
pcbasic/basic/base/__init__.py
pcbasic/basic/base/bytematrix.py
pcbasic/basic/base/bytestream.py
pcbasic/basic/base/codestream.py
pcbasic/basic/base/eascii.py
pcbasic/basic/base/error.py
pcbasic/basic/base/scancode.py
pcbasic/basic/base/signals.py
pcbasic/basic/base/tokens.py
pcbasic/basic/converter/__init__.py
pcbasic/basic/converter/lister.py
pcbasic/basic/converter/protect.py
pcbasic/basic/converter/tokeniser.py
pcbasic/basic/data/README.md
pcbasic/basic/data/__init__.py
pcbasic/basic/data/codepage.json
pcbasic/basic/data/font.json
pcbasic/basic/data/meta.json
pcbasic/basic/data/release.json
pcbasic/basic/devices/__init__.py
pcbasic/basic/devices/cassette.py
pcbasic/basic/devices/devicebase.py
pcbasic/basic/devices/disk.py
pcbasic/basic/devices/diskfiles.py
pcbasic/basic/devices/files.py
pcbasic/basic/devices/formatter.py
pcbasic/basic/devices/parports.py
pcbasic/basic/devices/ports.py
pcbasic/basic/display/__init__.py
pcbasic/basic/display/buffers.py
pcbasic/basic/display/colours.py
pcbasic/basic/display/cursor.py
pcbasic/basic/display/display.py
pcbasic/basic/display/font.py
pcbasic/basic/display/framebuffer.py
pcbasic/basic/display/graphics.py
pcbasic/basic/display/modes.py
pcbasic/basic/display/screencopyhandler.py
pcbasic/basic/display/textscreen.py
pcbasic/basic/inputs/__init__.py
pcbasic/basic/inputs/keyboard.py
pcbasic/basic/inputs/pen.py
pcbasic/basic/inputs/stick.py
pcbasic/basic/memory/__init__.py
pcbasic-2.0.7.dist-info/METADATA
pcbasic-2.0.7.dist-info/WHEEL
pcbasic-2.0.7.dist-info/entry_points.txt
pcbasic-2.0.7.dist-info/licenses/LICENSE.md
pcbasic-2.0.7.dist-info/RECORD
