Metadata-Version: 2.1
Name: pcbasic
Version: 2.0.7
Summary: A free, cross-platform emulator for the GW-BASIC family of interpreters.
Project-URL: Homepage, http://pc-basic.org
Project-URL: Bug Tracker, https://github.com/robhagemans/pcbasic/issues
Project-URL: Source Code, https://github.com/robhagemans/pcbasic/
Project-URL: Documentation, https://robhagemans.github.io/pcbasic/doc/2.0/
Author-email: Rob Hagemans <rob.hagemans@hotmail.com>
License: GPLv3
License-File: LICENSE.md
Keywords: basic,basica,emulator,gwbasic,interpreter,legacy,pcjr,retro,tandy
Classifier: Development Status :: 5 - Production/Stable
Classifier: Intended Audience :: Developers
Classifier: Intended Audience :: End Users/Desktop
Classifier: License :: OSI Approved :: GNU General Public License v3 (GPLv3)
Classifier: Programming Language :: Python :: 2.7
Classifier: Programming Language :: Python :: 3.6
Classifier: Topic :: Software Development :: Interpreters
Classifier: Topic :: System :: Emulators
Requires-Python: !=3.0.*,!=3.1.*,!=3.2.*,!=3.3.*,!=3.4.*,!=3.5.*,>=2.7.17
Requires-Dist: importlib-resources; python_version < '3.7'
Requires-Dist: pysdl2-dll
Requires-Dist: pyserial
Provides-Extra: dev
Requires-Dist: colorama; extra == 'dev'
Requires-Dist: coverage; extra == 'dev'
Requires-Dist: cx-freeze; extra == 'dev'
Requires-Dist: lxml; extra == 'dev'
Requires-Dist: markdown; extra == 'dev'
Requires-Dist: pillow; extra == 'dev'
Requires-Dist: pyaudio; extra == 'dev'
Requires-Dist: pylint; extra == 'dev'
Requires-Dist: pyparallel; extra == 'dev'
Requires-Dist: toml; extra == 'dev'
Provides-Extra: full
Requires-Dist: pyaudio; extra == 'full'
Requires-Dist: pyparallel; extra == 'full'
